md2json/__init__.py
md2json/md2json.py
proqtor/__init__.py
proqtor/core.py
proqtor/core_components.py
proqtor/evaluate_utils.py
proqtor/execute_utils.py
proqtor/gen_ai_utils.py
proqtor/parse.py
proqtor/prog_langs.py
proqtor/template_utils.py
proqtor/utils.py
proqtor/cli/__init__.py
proqtor/cli/cli.py
proqtor/cli/export.py
proqtor/data/runtimes.json
proqtor/templates/export_style.css
proqtor/templates/highlightjs_includes.html
proqtor/templates/katex_includes.html
proqtor/templates/proq_export_template.html.jinja
proqtor/templates/proq_template.md.jinja
proqtor/templates/python_tools.html
proqtor/templates/solution.md.jinja
proqtor/templates/lang_defaults/c.md
proqtor/templates/lang_defaults/java.md
proqtor/templates/lang_defaults/python.md
proqtor-2.2.0.dist-info/licenses/LICENSE
proqtor-2.2.0.dist-info/METADATA
proqtor-2.2.0.dist-info/WHEEL
proqtor-2.2.0.dist-info/entry_points.txt
proqtor-2.2.0.dist-info/top_level.txt
proqtor-2.2.0.dist-info/RECORD
