Metadata-Version: 2.4
Name: proqtor
Version: 2.2.0
Summary: A command-line based tool for authoring programming questions at scale.
Author-email: Livin Nector <livinnector2001@gmail.com>
Requires-Python: >=3.12
License-File: LICENSE
Requires-Dist: pyyaml
Requires-Dist: pydantic
Requires-Dist: fire
Requires-Dist: marko
Requires-Dist: Jinja2
Requires-Dist: strenum>=0.4.15
Requires-Dist: termcolor>=2.5.0
Requires-Dist: ipython~=8.0
Requires-Dist: unidecode>=1.4.0
Provides-Extra: genai
Requires-Dist: langchain-groq>=0.2.3; extra == "genai"
Requires-Dist: langchain-openai>=0.3.2; extra == "genai"
Requires-Dist: langchain>=0.3.15; extra == "genai"
Dynamic: license-file
